{
  "experiment": "exp_1_1_bell_basis",
  "timestamp": "2025-12-07T02:35:04.216210",
  "qiskit_available": true,
  "simulations": [
    {
      "name": "ideal_v1.0",
      "results": {
        "total_pairs": 10000,
        "key_samples": 9037,
        "security_samples": 963,
        "key_fraction": 0.9037,
        "key_analysis": {
          "matching_bases": 4620,
          "non_matching_bases": 4417,
          "sifting_rate": 0.5112316034082107,
          "agreement_matching": 1.0,
          "agreement_non_matching": 0.49581163685759566
        },
        "security_analysis": {
          "correlators": {
            "(0, 0)": {
              "value": 0.7083333333333334,
              "std": 0.045564235284234034,
              "n_samples": 240
            },
            "(0, 1)": {
              "value": -0.75,
              "std": 0.042001344064515445,
              "n_samples": 248
            },
            "(1, 0)": {
              "value": 0.6820083682008368,
              "std": 0.047306734582265905,
              "n_samples": 239
            },
            "(1, 1)": {
              "value": 0.7457627118644068,
              "std": 0.04336668533078136,
              "n_samples": 236
            }
          },
          "chsh_value": 2.886104413398577,
          "chsh_std": 0.08921215709576137,
          "tsirelson_bound": 2.828,
          "classical_bound": 2.0,
          "bell_violation": true,
          "efficiency": 1.020546115063146
        },
        "simulation_params": {
          "n_pairs": 10000,
          "key_fraction": 0.9,
          "visibility": 1.0,
          "seed": 42,
          "simulator": "IdealBellSimulator"
        }
      },
      "validation": {
        "passed": true,
        "checks": [
          {
            "name": "key_fraction",
            "expected": 0.9,
            "actual": 0.9037,
            "tolerance": 0.05,
            "passed": "True"
          },
          {
            "name": "matching_basis_agreement",
            "expected": ">0.95",
            "actual": 1.0,
            "passed": true
          },
          {
            "name": "non_matching_basis_agreement",
            "expected": "0.4-0.6",
            "actual": 0.49581163685759566,
            "passed": true
          },
          {
            "name": "chsh_value",
            "expected": "~2.828",
            "actual": 2.886104413398577,
            "passed": true
          },
          {
            "name": "bell_violation",
            "expected": true,
            "actual": true,
            "passed": true
          }
        ]
      }
    },
    {
      "name": "noisy_v0.9",
      "results": {
        "total_pairs": 10000,
        "key_samples": 9006,
        "security_samples": 994,
        "key_fraction": 0.9006,
        "key_analysis": {
          "matching_bases": 4421,
          "non_matching_bases": 4585,
          "sifting_rate": 0.49089495891627805,
          "agreement_matching": 0.9493327301515494,
          "agreement_non_matching": 0.4974918211559433
        },
        "security_analysis": {
          "correlators": {
            "(0, 0)": {
              "value": 0.688715953307393,
              "std": 0.04522620773822286,
              "n_samples": 257
            },
            "(0, 1)": {
              "value": -0.6581196581196581,
              "std": 0.04921948556170867,
              "n_samples": 234
            },
            "(1, 0)": {
              "value": 0.7370517928286853,
              "std": 0.04265840667572614,
              "n_samples": 251
            },
            "(1, 1)": {
              "value": 0.6428571428571429,
              "std": 0.04825258829629628,
              "n_samples": 252
            }
          },
          "chsh_value": 2.726744547112879,
          "chsh_std": 0.09282251646418364,
          "tsirelson_bound": 2.828,
          "classical_bound": 2.0,
          "bell_violation": true,
          "efficiency": 0.9641953844104948
        },
        "simulation_params": {
          "n_pairs": 10000,
          "key_fraction": 0.9,
          "visibility": 0.9,
          "seed": 43,
          "simulator": "IdealBellSimulator"
        }
      },
      "validation": {
        "passed": false,
        "checks": [
          {
            "name": "key_fraction",
            "expected": 0.9,
            "actual": 0.9006,
            "tolerance": 0.05,
            "passed": "True"
          },
          {
            "name": "matching_basis_agreement",
            "expected": ">0.95",
            "actual": 0.9493327301515494,
            "passed": false
          },
          {
            "name": "non_matching_basis_agreement",
            "expected": "0.4-0.6",
            "actual": 0.4974918211559433,
            "passed": true
          },
          {
            "name": "chsh_value",
            "expected": "~2.545",
            "actual": 2.726744547112879,
            "passed": true
          },
          {
            "name": "bell_violation",
            "expected": true,
            "actual": true,
            "passed": true
          }
        ]
      }
    },
    {
      "name": "qiskit_ideal",
      "results": {
        "total_pairs": 1000,
        "key_samples": 897,
        "security_samples": 103,
        "key_fraction": 0.897,
        "key_analysis": {
          "matching_bases": 422,
          "non_matching_bases": 475,
          "sifting_rate": 0.47045707915273133,
          "agreement_matching": 1.0,
          "agreement_non_matching": 0.5242105263157895
        },
        "security_analysis": {
          "correlators": {
            "(0, 0)": {
              "value": 0.5555555555555556,
              "std": 0.1600182888495768,
              "n_samples": 27
            },
            "(0, 1)": {
              "value": -0.5833333333333334,
              "std": 0.16579633869879618,
              "n_samples": 24
            },
            "(1, 0)": {
              "value": 0.7931034482758621,
              "std": 0.11310460832907601,
              "n_samples": 29
            },
            "(1, 1)": {
              "value": 0.9130434782608695,
              "std": 0.0850451559864045,
              "n_samples": 23
            }
          },
          "chsh_value": 2.8450358154256206,
          "chsh_std": 0.2704063787603726,
          "tsirelson_bound": 2.828,
          "classical_bound": 2.0,
          "bell_violation": true,
          "efficiency": 1.0060239799949153
        },
        "simulation_params": {
          "n_pairs": 1000,
          "key_fraction": 0.9,
          "noise_level": 0.0,
          "seed": 44,
          "simulator": "QKDSimulator (Qiskit Aer)"
        }
      },
      "validation": {
        "passed": true,
        "checks": [
          {
            "name": "key_fraction",
            "expected": 0.9,
            "actual": 0.897,
            "tolerance": 0.05,
            "passed": "True"
          },
          {
            "name": "matching_basis_agreement",
            "expected": ">0.95",
            "actual": 1.0,
            "passed": true
          },
          {
            "name": "non_matching_basis_agreement",
            "expected": "0.4-0.6",
            "actual": 0.5242105263157895,
            "passed": true
          },
          {
            "name": "chsh_value",
            "expected": "~2.828",
            "actual": 2.8450358154256206,
            "passed": true
          },
          {
            "name": "bell_violation",
            "expected": true,
            "actual": true,
            "passed": true
          }
        ]
      }
    }
  ],
  "summary": {
    "simulations_run": 3,
    "simulations_passed": 2,
    "overall_passed": false
  }
}